MANIFEST.in
README.md
VERSION
setup.cfg
setup.py
aakr/__init__.py
aakr/_aakr.py
aakr.egg-info/PKG-INFO
aakr.egg-info/SOURCES.txt
aakr.egg-info/dependency_links.txt
aakr.egg-info/requires.txt
aakr.egg-info/top_level.txt
tests/__init__.py
tests/test_aakr.py