Metadata-Version: 2.1
Name: aakr
Version: 0.0.1.dev3
Summary: Implementation of Auto Associative Kernel Regression (AAKR)
Home-page: https://github.com/jmyrberg/aakr
Author: Jesse Myrberg
Author-email: jesse.myrberg@gmail.com
License: MIT
Keywords: aakr,auto,associative,kernel,regression,anomaly,detection
Platform: UNKNOWN
Classifier: Development Status :: 2 - Pre-Alpha
Classifier: Programming Language :: Python :: 3
Classifier: License :: OSI Approved :: MIT License
Classifier: Intended Audience :: Science/Research
Classifier: Intended Audience :: Developers
Classifier: License :: OSI Approved
Classifier: Topic :: Software Development
Classifier: Topic :: Scientific/Engineering
Classifier: Operating System :: Microsoft :: Windows
Classifier: Operating System :: POSIX
Classifier: Operating System :: Unix
Classifier: Operating System :: MacOS
Provides-Extra: tests
Provides-Extra: docs
